hsc/__init__.py
hsc/__main__.py
hsc/constants.py
hsc/crawler.py
hsc/metadata.py
hsc/progress_bar.py
hsc-1.2.5.dist-info/LICENSE
hsc-1.2.5.dist-info/METADATA
hsc-1.2.5.dist-info/WHEEL
hsc-1.2.5.dist-info/entry_points.txt
hsc-1.2.5.dist-info/top_level.txt
hsc-1.2.5.dist-info/RECORD
