Metadata-Version: 2.1
Name: hsc
Version: 1.2.5
Summary: Hackerrank Solution Crawler
Home-page: https://github.com/Nullifiers/Hackerrank-Solution-Crawler
Author: Nullifiers
Author-email: nullifiersorg@gmail.com
License: UNKNOWN
Download-URL: https://github.com/Nullifiers/Hackerrank-Solution-Crawler/releases
Platform: UNKNOWN
Classifier: Programming Language :: Python :: 3
Classifier: License :: OSI Approved :: MIT License
Classifier: Operating System :: OS Independent
License-File: LICENSE
Requires-Dist: progress
Requires-Dist: requests
Requires-Dist: configargparse
